SummerSearch/SummerSearch.py
SummerSearch/__init__.py
summer_search-0.0.4.dist-info/METADATA
summer_search-0.0.4.dist-info/WHEEL
summer_search-0.0.4.dist-info/top_level.txt
summer_search-0.0.4.dist-info/RECORD
