Metadata-Version: 2.1
Name: summer-search
Version: 0.0.4
Summary: Search and summarize the web with ease!
Author: Cozmic (Hem Sainath)
Author-email: hemsainath15@gmail.com
Keywords: python,search,summerisation,summary,ml,information
Classifier: Development Status :: 3 - Alpha
Classifier: Intended Audience :: Developers
Classifier: Programming Language :: Python :: 3
Classifier: Operating System :: Unix
Classifier: Operating System :: MacOS :: MacOS X
Classifier: Operating System :: Microsoft :: Windows
Requires-Dist: bs4
Requires-Dist: requests
Requires-Dist: transformers
Requires-Dist: sentencepiece
Requires-Dist: tensorflow
Requires-Dist: torch
